odoo/addons/product_state/README.rst
odoo/addons/product_state/__init__.py
odoo/addons/product_state/__manifest__.py
odoo/addons/product_state/i18n/de.po
odoo/addons/product_state/i18n/es.po
odoo/addons/product_state/i18n/fr.po
odoo/addons/product_state/i18n/hr.po
odoo/addons/product_state/i18n/nl_NL.po
odoo/addons/product_state/i18n/sl.po
odoo/addons/product_state/models/__init__.py
odoo/addons/product_state/models/product_template.py
odoo/addons/product_state/views/product_views.xml
odoo11_addon_product_state-11.0.1.0.0.dist-info/DESCRIPTION.rst
odoo11_addon_product_state-11.0.1.0.0.dist-info/METADATA
odoo11_addon_product_state-11.0.1.0.0.dist-info/RECORD
odoo11_addon_product_state-11.0.1.0.0.dist-info/WHEEL
odoo11_addon_product_state-11.0.1.0.0.dist-info/metadata.json
odoo11_addon_product_state-11.0.1.0.0.dist-info/top_level.txt
